{"Equipment":{"tags":["default"]},"Item":{"tags":["default"]},"AbstractAmulet":{"tags":["default","amulet"]},"AbstractArmour":{"tags":["default","armour"]},"AbstractBodyArmour":{"tags":["default","armour","body_armour"]},"AbstractBoots":{"tags":["default","armour","boots"]},"AbstractGloves":{"tags":["default","armour","gloves"]},"AbstractHelmet":{"tags":["default","armour","helmet"]},"AbstractShield":{"tags":["default","armour","shield"]},"AbstractBelt":{"tags":["default","belt"]},"AbstractCurrency":{"tags":["default"]},"AbstractMicrotransaction":{"tags":["default"]},"CurrencyImprint":{"tags":["default","currency"]},"StackableCurrency":{"tags":["default","currency"]},"AbstractDivinationCard":{"tags":["default","divination_card"]},"AbstractFlask":{"tags":["default","flask"]},"AbstractHybridFlask":{"tags":["default","flask","hybrid_flask"]},"AbstractLifeFlask":{"tags":["default","flask","life_flask"]},"AbstractManaFlask":{"tags":["default","flask","mana_flask"]},"AbstractUtilityFlask":{"tags":["default","flask","utility_flask"]},"CriticalUtilityFlask":{"tags":["default","flask","utility_flask","critical_utility_flask"]},"FlaskUtility1":{"tags":["default","flask","utility_flask"]},"AbstractSkillGem":{"tags":["default","gem"]},"ActiveSkillGem":{"tags":["default","gem"]},"SupportSkillGem":{"tags":["default","gem","support_gem"]},"AbstractHideoutDoodad":{"tags":["default"]},"AbstractJewel":{"tags":["default"]},"AbstractMapFragment":{"tags":["default"]},"AbstractMap":{"tags":["default","map"]},"MysteryBox1x1":{"tags":["default","currency"]},"MysteryBox1x2":{"tags":["default","currency"]},"MysteryBox1x3":{"tags":["default","currency"]},"MysteryBox1x4":{"tags":["default","currency"]},"MysteryBox2x1":{"tags":["default","currency"]},"MysteryBox2x2":{"tags":["default","currency"]},"MysteryBox2x3":{"tags":["default","currency"]},"MysteryBox2x4":{"tags":["default","currency"]},"MysteryBox3x2":{"tags":["default","currency"]},"MysteryBox3x3":{"tags":["default","currency"]},"AbstractQuestItem":{"tags":["default"]},"AllFlameLantern1":{"tags":["default"]},"GoldenHand":{"tags":["default"]},"InfernalTalc":{"tags":["default"]},"MedicineSet1":{"tags":["default"]},"PoisonSkillGem":{"tags":["default"]},"PoisonSpear":{"tags":["default"]},"RibbonSpool":{"tags":["default"]},"SewerKeys":{"tags":["default"]},"SpikeSealKey":{"tags":["default"]},"SulphiteFlask":{"tags":["default"]},"TolmanBracelet":{"tags":["default"]},"TowerKey":{"tags":["default"]},"Book-a4q6":{"tags":["default"]},"DaressoGem":{"tags":["default"]},"KaomGem":{"tags":["default"]},"Organ1":{"tags":["default"]},"Organ2":{"tags":["default"]},"Organ3":{"tags":["default"]},"RedBanner":{"tags":["default"]},"CombinedAmulet":{"tags":["default"]},"DexAmulet":{"tags":["default"]},"IntAmulet":{"tags":["default"]},"StrAmulet":{"tags":["default"]},"Bust1":{"tags":["default"]},"Bust2":{"tags":["default"]},"Bust3":{"tags":["default"]},"Decanter":{"tags":["default"]},"Fruit":{"tags":["default"]},"Glyph1":{"tags":["default"]},"Glyph2":{"tags":["default"]},"Glyph3":{"tags":["default"]},"Page1":{"tags":["default"]},"Page2":{"tags":["default"]},"Page3":{"tags":["default"]},"Page4":{"tags":["default"]},"BanditRespecAlira":{"tags":["default"]},"BanditRespecEramir":{"tags":["default"]},"BanditRespecKraityn":{"tags":["default"]},"BanditRespecOak":{"tags":["default"]},"Book-a1q6":{"tags":["default"]},"Book-a1q7":{"tags":["default"]},"Book-a1q8":{"tags":["default"]},"Book-a1q9":{"tags":["default"]},"Book-a2q5":{"tags":["default"]},"Book-a3q11v0":{"tags":["default"]},"Book-a3q11v1":{"tags":["default"]},"Book-a3q11v2":{"tags":["default"]},"Book-a3q9":{"tags":["default"]},"Descent2_1":{"tags":["default"]},"Descent2_2":{"tags":["default"]},"Descent2_3":{"tags":["default"]},"Descent2_4":{"tags":["default"]},"AbstractQuiver":{"tags":["default","quiver"]},"AbstractRelic":{"tags":["default","relic"]},"AbstractLargeRelic":{"tags":["default","relic"]},"AbstractMediumRelic":{"tags":["default","relic"]},"AbstractSmallRelic":{"tags":["default","relic"]},"AbstractRing":{"tags":["default","ring"]},"AbstractSocketableRing":{"tags":["default","ring"]},"Ring15":{"tags":["default","ring"]},"AbstractWeapon":{"tags":["default","weapon"]},"AbstractOneHandWeapon":{"tags":["default","weapon","onehand"]},"AbstractClaw":{"tags":["default","weapon","onehand","claw","one_hand_weapon"]},"AbstractDagger":{"tags":["default","weapon","onehand","dagger","one_hand_weapon"]},"AbstractOneHandAxe":{"tags":["default","weapon","onehand","axe","one_hand_weapon"]},"AbstractOneHandMace":{"tags":["default","weapon","onehand","mace","one_hand_weapon"]},"AbstractSceptre":{"tags":["default","weapon","onehand","sceptre","one_hand_weapon"]},"AbstractOneHandSword":{"tags":["default","weapon","onehand","sword","one_hand_weapon"]},"AbstractOneHandSwordThrusting":{"tags":["default","weapon","onehand","sword","one_hand_weapon"]},"AbstractWand":{"tags":["default","weapon","onehand","wand","ranged","one_hand_weapon"]},"AbstractTwoHandWeapon":{"tags":["default","weapon","twohand"]},"AbstractBow":{"tags":["default","weapon","twohand","bow","ranged","two_hand_weapon"]},"AbstractFishingRod":{"tags":{"0":"default","2":"twohand","4":"fishing_rod"}},"AbstractStaff":{"tags":["default","weapon","twohand","staff","two_hand_weapon"]},"Staff1":{"tags":["default","weapon","twohand","staff","two_hand_weapon"]},"AbstractTwoHandAxe":{"tags":["default","weapon","twohand","axe","two_hand_weapon"]},"AbstractTwoHandMace":{"tags":["default","weapon","twohand","mace","two_hand_weapon"]},"AbstractTwoHandSword":{"tags":["default","weapon","twohand","sword","two_hand_weapon"]},"TwoHandSword1":{"tags":["default","weapon","twohand","sword","two_hand_weapon"]}}